TEA_Analysis/TEA_Analysis.py
TEA_Analysis/__init__.py
TEA_Analysis-0.0.3.dist-info/LICENSE
TEA_Analysis-0.0.3.dist-info/METADATA
TEA_Analysis-0.0.3.dist-info/WHEEL
TEA_Analysis-0.0.3.dist-info/top_level.txt
TEA_Analysis-0.0.3.dist-info/RECORD
